odoo/addons/sale_stock_service_level/README.rst
odoo/addons/sale_stock_service_level/__init__.py
odoo/addons/sale_stock_service_level/__manifest__.py
odoo/addons/sale_stock_service_level/i18n/fr.po
odoo/addons/sale_stock_service_level/i18n/sale_stock_service_level.pot
odoo/addons/sale_stock_service_level/models/__init__.py
odoo/addons/sale_stock_service_level/models/sale_order.py
odoo/addons/sale_stock_service_level/models/sale_order_line.py
odoo/addons/sale_stock_service_level/readme/CONTRIBUTORS.rst
odoo/addons/sale_stock_service_level/readme/DESCRIPTION.rst
odoo/addons/sale_stock_service_level/static/description/icon.png
odoo/addons/sale_stock_service_level/static/description/index.html
odoo/addons/sale_stock_service_level/tests/__init__.py
odoo/addons/sale_stock_service_level/tests/test_sale_stock_service_level.py
odoo/addons/sale_stock_service_level/views/sale_order_views.xml
odoo14_addon_sale_stock_service_level-14.0.0.1.1.dev2.dist-info/METADATA
odoo14_addon_sale_stock_service_level-14.0.0.1.1.dev2.dist-info/WHEEL
odoo14_addon_sale_stock_service_level-14.0.0.1.1.dev2.dist-info/top_level.txt
odoo14_addon_sale_stock_service_level-14.0.0.1.1.dev2.dist-info/RECORD
