Metadata-Version: 2.1
Name: odoo14-addon-sale_stock_service_level
Version: 14.0.0.1.1.dev2
Summary: Sale stock service level
Home-page: https://github.com/OCA/sale-workflow
Author: Pierre Verkest <pierreverkest84@gmail.com>, Odoo Community Association (OCA)
Author-email: support@odoo-community.org
License: AGPL-3
Classifier: Programming Language :: Python
Classifier: Framework :: Odoo
Classifier: Framework :: Odoo :: 14.0
Classifier: License :: OSI Approved :: GNU Affero General Public License v3
Classifier: Development Status :: 4 - Beta
Requires-Python: >=3.6
Requires-Dist: odoo14-addon-stock-service-level
Requires-Dist: odoo<14.1dev,>=14.0a
